README.rst
setup.py
tempest_graph/TempestService.py
tempest_graph/__init__.py
tempest_graph/constants.py
tempest_graph/ttypes.py
tempest_graph.egg-info/PKG-INFO
tempest_graph.egg-info/SOURCES.txt
tempest_graph.egg-info/dependency_links.txt
tempest_graph.egg-info/requires.txt
tempest_graph.egg-info/top_level.txt