Metadata-Version: 1.1
Name: tempest-graph
Version: 0.9.0
Summary: Python client for the Tempest Graph Library
Home-page: https://github.com/teapot-co/tempest
Author: Peter Lofgren
Author-email: plofgren@cs.stanford.edu
License: Apache
Keywords: graph network
Platform: UNKNOWN
Classifier: Development Status :: 4 - Beta
Classifier: License :: OSI Approved :: Apache Software License
Classifier: Programming Language :: Python :: 2
Classifier: Programming Language :: Python :: 2.6
Classifier: Programming Language :: Python :: 2.7
